pypion/PlotData.py
pypion/Plotting_Classes.py
pypion/ReadData.py
pypion/SiloHeader_data.py
pypion/__init__.py
pypion/argparse_command.py
pypion-1.1.0.dist-info/LICENSE.md
pypion-1.1.0.dist-info/METADATA
pypion-1.1.0.dist-info/WHEEL
pypion-1.1.0.dist-info/top_level.txt
pypion-1.1.0.dist-info/RECORD
