Metadata-Version: 2.1
Name: pypion
Version: 1.1.0
Summary: Python package to open Silo data files from PION
Home-page: https://git.dias.ie/massive-stars-software/pypion
Author: Sam Green
Author-email: green@cp.dias.ie
Project-URL: Bug Tracker, https://git.dias.ie/massive-stars-software/pypion/-/boards
Classifier: Programming Language :: Python :: 3
Classifier: License :: OSI Approved :: MIT License
Classifier: Operating System :: OS Independent
Requires-Python: >=3.6
License-File: LICENSE.md
Requires-Dist: numpy
Requires-Dist: astropy
